Workbook

Sheet Summary
A1: Fox Cities Racquet Club - BRD Review & India-Based Odoo Cost Estimate
A3: Item | B3: Value | D3: Executive Review
A4: Prepared from | B4: Fox Cities Racquet Club BRD PDF v1.0 | D4: - BRD is broad and valid for an integrated Odoo ERP, but court scheduling is the main custom-risk area.
A5: Prepared date | B5: 2026-07-17 | D5: - Odoo can cover CRM, contacts, subscriptions, POS, inventory, purchase, accounting, documents, approvals, reporting and HR with configuration plus targeted custom work.
A6: Delivery model | B6: India offshore/remote implementation | D6: - Membership rules, family/household accounts, court booking windows, league schedules, waitlists, and utilization reporting require deeper fit-gap workshops.
A7: Commercial currency | B7: USD quote with INR reference | D7: - US payroll, payment terminals, Sage 50 migration, and online member booking should be confirmed before final quote.
A8: FX assumption | B8: 1 USD = INR 83.50 (editable) | D8: - India-based delivery materially reduces implementation cost compared with a US-rate estimate; license cost remains vendor/subscription driven.
A9: Recommended Odoo plan | B9: Custom, annual billing
A10: Planning paid users | B10: 12
A12: Cost Summary - India Delivery
A13: Line Item | B13: USD | C13: INR Reference
A14: Implementation subtotal | B14: ='Implementation Cost'!K22 | C14: =B13*Assumptions!$B$5
A15: Implementation contingency | B15: ='Implementation Cost'!K23 | C15: =B14*Assumptions!$B$5
A16: Implementation total | B16: ='Implementation Cost'!K24 | C16: =B15*Assumptions!$B$5
A17: Recommended Odoo license, year 1 | B17: ='Odoo License Cost'!E13 | C17: =B16*Assumptions!$B$5
A18: Hardware/third-party placeholder | B18: ='Hardware & Third Party'!E16 | C18: =B17*Assumptions!$B$5
A19: Estimated first-year total | B19: =B16+B17+B18 | C19: =C16+C17+C18
A20: Recurring annual license only | B20: ='Odoo License Cost'!E13 | C20: =B19*Assumptions!$B$5

Sheet BRD Review
A1: Area | B1: Review Finding | C1: Action / Recommendation
A2: Overall | B2: Strong BRD with clear business objectives, KPIs, current-state challenges, scope, roles, functional requirements, non-functional requirements, migration and acceptance criteria. | C2: Use as phase-0 scope baseline, then conduct fit-gap workshops.
A3: Scope | B3: In scope includes CRM, memberships, court scheduling, programs, POS, inventory, purchasing, accounting, payroll, reporting, documents and communications. | C3: Treat as multi-phase ERP implementation; avoid one-shot go-live.
A4: Configuration-first principle | B4: BRD explicitly prefers standard Odoo configuration before customization. | C4: Use Odoo standard apps first; document every custom gap with business justification.
A5: Largest functional gap | B5: Court scheduling/reservations with double-booking prevention, booking privileges, waitlists, instructor schedules and utilization analytics. | C5: Prototype early and confirm whether Appointments/Planning plus custom module is acceptable.
A6: Financial complexity | B6: Sage 50 migration, opening balances, AR/AP, inventory valuation, bank reconciliation and month-end close are critical. | C6: Assign dedicated accounting SME and perform mock financial reconciliation.
A7: Payroll complexity | B7: BRD requires payroll calculations, leave balances and GL posting. | C7: Confirm US payroll compliance/provider strategy before final implementation scope.
A8: Data migration | B8: Customer, household, vendor, inventory, membership, AR/AP, GL and employee data migration are required. | C8: Request sample exports immediately; define cleansing ownership.
A9: Acceptance criteria | B9: BRD includes UAT, financial reconciliation, scheduling validation, POS testing and 30-day stabilization. | C9: Build formal UAT scripts and sign-off gates into project plan.

Sheet Fit Gap
A1: Workstream | B1: Likely Odoo Apps | C1: Fit Level | D1: Key BRD Needs | E1: Complexity | F1: India Delivery Recommendation
A2: CRM & Customer Master | B2: Contacts, CRM, Documents | C2: Partial configuration | D2: Duplicate detection, family/household links, customer lifetime history, document attachment rules | E2: Medium | F2: Configure contacts/customer hierarchy; add custom fields/views for family/household and membership context.
A3: Membership Management | B3: Subscriptions, Sales, Invoicing, Portal | C3: Partial/custom | D3: Membership types, privileges, renewals, guest rules, automatic billing, member statements | E3: High | F3: Use subscriptions for recurring billing; customize privileges and reservation rules.
A4: Court Scheduling | B4: Appointments, Planning, Calendar, Portal | C4: Custom-heavy | D4: Court resources, conflict prevention, recurring reservations, waitlist, maintenance blocks, member booking windows | E4: Very High | F4: Build prototype as first high-risk sprint.
A5: Programs / Lessons / Leagues | B5: Planning, Events, Sales, Project | C5: Partial/custom | D5: Private/group lessons, clinics, league scheduling, attendance and instructor assignments | E5: High | F5: Define program templates and scheduling rules in fit-gap.
A6: Point of Sale | B6: POS, Barcode, Sales, Payments | C6: Mostly standard | D6: Barcode scanning, member pricing, discounts, returns, gift cards, payment processing | E6: Medium | F6: Confirm hardware and processor compatibility.
A7: Inventory & Purchasing | B7: Inventory, Purchase, Barcode, Accounting | C7: Mostly standard | D7: Receiving, adjustments, valuation, reorder rules, PO/vendor bill matching | E7: Medium | F7: Configure product categories, stock locations and valuation method.
A8: Accounting | B8: Accounting, Invoicing, Approvals | C8: Mostly standard | D8: AR/AP, GL, bank reconciliation, reminders, approvals, statements | E8: Medium | F8: Map Sage 50 chart of accounts and closing process.
A9: Payroll & HR | B9: Employees, Time Off, Payroll/Provider | C9: Partial/custom/provider | D9: Payroll calculation, leave balances, GL posting, approvals | E9: High | F9: Confirm US payroll compliance and provider/API.
A10: Reporting | B10: Spreadsheet BI, Dashboards, Accounting Reports | C10: Partial configuration | D10: Executive dashboards, court utilization, memberships, instructor productivity, inventory, financials | E10: Medium | F10: Define KPI formulas and dashboard mockups.
A11: Documents & Waivers | B11: Documents, Sign, Contacts | C11: Mostly standard | D11: Waivers, contracts, correspondence attached to customer records | E11: Medium | F11: Use document workspaces and Sign templates where possible.
A12: Customer Portal / Online Booking | B12: Portal, Website, Appointments | C12: Partial/custom | D12: Real-time account access, optional online reservations, notifications | E12: High | F12: Confirm if online booking is phase 1 or later.
A13: Security & Approvals | B13: Users, Groups, Approvals | C13: Configuration | D13: General Manager, Pro Shop/Accounting, Front Desk/POS, least privilege and approvals | E13: Medium | F13: Create role matrix and test with users.

Sheet Implementation Cost
A1: WBS | B1: Workstream | C1: BRD Coverage | D1: Scope Included | E1: Odoo Apps / Components | F1: Low Hours | G1: Base Hours | H1: High Hours | I1: Risk | J1: Notes | K1: Base Cost USD | L1: Base Cost INR
A2: DISC | B2: Discovery, BRD validation & solution blueprint | C2: All sections | D2: Process workshops, fit-gap, traceability, solution design, backlog and project plan | E2: Project, Knowledge | F2: 60 | G2: 90 | H2: 120 | I2: Medium | J2: India remote workshops; onsite travel excluded. | K2: =G2*Assumptions!$B$3 | L2: =K2*Assumptions!$B$5
A3: PM | B3: Project management & governance | C3: All workstreams | D3: Status meetings, RAID, change control, steering reviews, budget/schedule management | E3: Project | F3: 55 | G3: 80 | H3: 110 | I3: Medium | J3: Remote governance. | K3: =G3*Assumptions!$B$3 | L3: =K3*Assumptions!$B$5
A4: BASE | B4: Base Odoo setup & environment configuration | C4: NFR, Security, Maintainability | D4: Company setup, fiscal settings, users, email templates, system parameters, backup/cutover settings | E4: Settings, Discuss, Documents | F4: 35 | G4: 50 | H4: 70 | I4: Low | J4: Odoo.sh/on-prem hosting excluded unless selected. | K4: =G4*Assumptions!$B$3 | L4: =K4*Assumptions!$B$5
A5: CRM | B5: CRM, customer records & family relationships | C5: BR-CRM-001 to BR-CRM-005 | D5: Customer master, duplicate controls, family links, archive rules, history, communications, documents | E5: CRM, Contacts, Documents | F5: 95 | G5: 135 | H5: 180 | I5: High | J5: Family/household logic may require custom fields. | K5: =G5*Assumptions!$B$3 | L5: =K5*Assumptions!$B$5
A6: MEM | B6: Membership management & recurring billing | C6: BR-CRM-006, Membership scope | D6: Membership types, privileges, annual/monthly billing, renewals, guest handling, balances, statements | E6: Subscriptions, Invoicing, Sales | F6: 90 | G6: 130 | H6: 175 | I6: High | J6: Use subscriptions; customize privilege logic. | K6: =G6*Assumptions!$B$3 | L6: =K6*Assumptions!$B$5
A7: COURT | B7: Court scheduling & reservations | C7: BR-COURT-001 to BR-COURT-006 | D7: Courts/resources, calendar, recurring bookings, booking windows, conflict prevention, maintenance blocks, waitlists | E7: Appointments, Planning, Calendar, Portal | F7: 170 | G7: 240 | H7: 330 | I7: High | J7: Largest custom-risk area. | K7: =G7*Assumptions!$B$3 | L7: =K7*Assumptions!$B$5
A8: PROG | B8: Programs, instruction, lessons, clinics & leagues | C8: Programs and Instruction scope | D8: Private/group lessons, clinics, junior/adult programs, league administration, attendance, instructor assignment | E8: Planning, Events, Sales, Project | F8: 110 | G8: 155 | H8: 220 | I8: High | J8: League scheduling may need custom rules. | K8: =G8*Assumptions!$B$3 | L8: =K8*Assumptions!$B$5
A9: POS | B9: Point of Sale retail operations | C9: BR-POS-001 to BR-POS-006 | D9: POS, barcode scanning, member pricing, discounts, gift cards, returns/exchanges, payment flow | E9: POS, Sales, Payments | F9: 75 | G9: 105 | H9: 145 | I9: Medium | J9: Payment terminal provider excluded. | K9: =G9*Assumptions!$B$3 | L9: =K9*Assumptions!$B$5
A10: INV | B10: Inventory & purchasing | C10: BR-INV-001 to BR-INV-006 | D10: Products, SKUs, stock locations, receiving, adjustments, valuation, reorder rules, POs, vendor bill match | E10: Inventory, Purchase, Barcode, Accounting | F10: 95 | G10: 135 | H10: 185 | I10: Medium | J10: Covers retail/teaching/office/maintenance inventory. | K10: =G10*Assumptions!$B$3 | L10: =K10*Assumptions!$B$5
A11: ACC | B11: Accounting, AR/AP, GL & bank reconciliation | C11: BR-ACC-001 to BR-ACC-009 | D11: CoA, AR/AP, customer invoices, payments, reminders, vendor bills, approvals, bank reconciliation, reports | E11: Accounting, Invoicing, Approvals | F11: 120 | G11: 165 | H11: 230 | I11: High | J11: Sage 50 reconciliation required. | K11: =G11*Assumptions!$B$3 | L11: =K11*Assumptions!$B$5
A12: PAY | B12: Payroll & HR | C12: BR-ACC-010 to BR-ACC-013 | D12: Employee records, payroll rules, leave balances, payroll approval, GL posting, payroll reporting | E12: Employees, Payroll, Time Off | F12: 70 | G12: 105 | H12: 155 | I12: High | J12: US payroll provider/compliance to confirm. | K12: =G12*Assumptions!$B$3 | L12: =K12*Assumptions!$B$5
A13: DOC | B13: Documents, waivers, contracts & e-signature | C13: BR-CRM-005, Documentation | D13: Document folders, waivers/contracts, attachment rules, document history, e-sign workflow | E13: Documents, Sign, Contacts | F13: 45 | G13: 70 | H13: 100 | I13: Medium | J13: Use Odoo Sign where possible. | K13: =G13*Assumptions!$B$3 | L13: =K13*Assumptions!$B$5
... A20: GO | B20: Cutover, go-live & 30-day stabilization | C20: Cutover Strategy, Overall Acceptance | D20: Go-live checklist, final migration, freeze window, launch support, 30-day stabilization | E20: All modules | F20: 70 | G20: 105 | H20: 150 | I20: High | J20: Post-go-live support window included. | K20: =G20*Assumptions!$B$3 | L20: =K20*Assumptions!$B$5
J22: Implementation subtotal | K22: =SUM(K2:K20) | L22: =K22*Assumptions!$B$5
J23: Contingency | K23: =K22*Assumptions!$B$4 | L23: =K23*Assumptions!$B$5
J24: Implementation total | K24: =K22+K23 | L24: =K24*Assumptions!$B$5

Sheet Odoo License Cost
A1: Setting | B1: Value | C1: Notes
A2: Planning paid internal users | B2: 12 | C2: Editable; BRD has roles but no exact headcount.
A3: Standard annual billing price per user/month USD | B3: 24.9 | C3: Planning rate; confirm final quote.
A4: Standard monthly billing price per user/month USD | B4: 31.1 | C4: Comparison only.
A5: Custom annual billing price per user/month USD | B5: 37.4 | C5: Recommended planning rate.
A6: Custom monthly billing price per user/month USD | B6: 46.8 | C6: Comparison only.
A7: FX rate USD to INR | B7: 83.5 | C7: Editable assumption.
A10: Plan | B10: Included | C10: Billing | D10: Monthly USD | E10: Annual USD | F10: Annual INR Ref | G10: Notes
A11: One App Free | B11: One app only | C11: N/A | D11: =0 | E11: =0 | F11: =E10*$B$7 | G11: Not suitable for this BRD.
A12: Standard | B12: All apps, Odoo Online | C12: Annual | D12: =B$2*B$3 | E12: =D11*12 | F12: =E11*$B$7 | G12: Comparison only; no custom modules/API/Studio.
A13: Standard | B13: All apps, Odoo Online | C13: Monthly | D13: =B$2*B$4 | E13: =D12*12 | F13: =E12*$B$7 | G13: Comparison only.
A14: Custom - Recommended | B14: All apps, Odoo Online/Odoo.sh/on-premise, Studio, Multi-Company, External API | C14: Annual | D14: =B$2*B$5 | E14: =D13*12 | F14: =E13*$B$7 | G14: Recommended due BRD customization/integration needs.
A15: Custom | B15: All apps, Odoo Online/Odoo.sh/on-premise, Studio, Multi-Company, External API | C15: Monthly | D15: =B$2*B$6 | E15: =D14*12 | F15: =E14*$B$7 | G15: Comparison only.
A16: Odoo.sh hosting | B16: Hosting for custom modules | C16: Quote required | D16: =0 | E16: =0 | F16: =E15*$B$7 | G16: Not included in license.
A18: Topic | B18: Note
A19: License note | B19: Odoo subscription is a vendor cost, separate from India implementation services.
A20: Billing country | B20: If the license is contracted in India, request an official INR quote from Odoo; if contracted by the US client, use the applicable US quote.
A21: Portal users | B21: Customer/member portal users are not treated as paid backend users for this estimate.
A22: Exclusions | B22: Implementation services, IAP/SMS credits, Odoo.sh hosting, and custom-code maintenance are excluded from license pricing.

Sheet Hardware & Third Party
A1: Category | B1: Item | C1: Qty | D1: Unit Cost USD | E1: Estimated Cost USD | F1: Estimated INR Ref | G1: Notes
A2: POS Hardware | B2: Barcode scanners | C2: 2 | D2: 175 | E2: =C2*D2 | F2: =E2*Assumptions!$B$5 | G2: Needed for BR-POS-001; client-local procurement.
A3: POS Hardware | B3: Receipt printers | C3: 2 | D3: 300 | E3: =C3*D3 | F3: =E3*Assumptions!$B$5 | G3: Estimate only.
A4: POS Hardware | B4: Cash drawers | C4: 2 | D4: 150 | E4: =C4*D4 | F4: =E4*Assumptions!$B$5 | G4: Estimate only.
A5: POS Hardware | B5: Label printer for inventory/barcodes | C5: 1 | D5: 450 | E5: =C5*D5 | F5: =E5*Assumptions!$B$5 | G5: For SKU/barcode labels.
A6: POS Hardware | B6: POS terminal/tablet/computer allowance | C6: 2 | D6: 850 | E6: =C6*D6 | F6: =E6*Assumptions!$B$5 | G6: Use existing hardware if compatible.
A7: Payments | B7: Payment terminals | C7: 2 | D7: 0 | E7: =C7*D7 | F7: =E7*Assumptions!$B$5 | G7: Processor/provider quote required.
A8: Communications | B8: SMS / IAP credits | C8: 1 | D8: 0 | E8: =C8*D8 | F8: =E8*Assumptions!$B$5 | G8: Excluded from license.
A9: Payroll | B9: US payroll provider/subscription | C9: 1 | D9: 0 | E9: =C9*D9 | F9: =E9*Assumptions!$B$5 | G9: Provider cost to confirm.
A10: Data | B10: Sage 50 export/support assistance | C10: 1 | D10: 0 | E10: =C10*D10 | F10: =E10*Assumptions!$B$5 | G10: May be client/vendor task.
A11: Travel | B11: Onsite travel and expenses | C11: 1 | D11: 0 | E11: =C11*D11 | F11: =E11*Assumptions!$B$5 | G11: Remote India delivery assumed.
A12: Contingency | B12: Hardware contingency | C12: 1 | D12: =SUM(E2:E11)*0.10 | E12: =C12*D12 | F12: =E12*Assumptions!$B$5 | G12: 10% placeholder contingency.
D16: Total | E16: =SUM(E2:E12) | F16: =E16*Assumptions!$B$5

Sheet Phasing
A1: Phase | B1: BRD Priority | C1: Workstreams | D1: Target Outcome | E1: Base Hours | F1: Cost USD | G1: Cost INR Ref | H1: Notes
A2: Phase 0 | B2: Initiation | C2: Discovery, blueprint, project governance, base setup | D2: Validated scope, backlog and environment readiness | E2: =SUM('Implementation Cost'!G2:G4) | F2: =E2*Assumptions!$B$3 | G2: =F2*Assumptions!$B$5 | H2: Remote India workshops.
A3: Phase 1 | B3: Core Operations | C3: CRM, memberships, court scheduling, programs, POS, inventory, AR/customer billing | D3: Daily operations ready for UAT | E3: =SUM('Implementation Cost'!G5:G10) | F3: =E3*Assumptions!$B$3 | G3: =F3*Assumptions!$B$5 | H3: Core operational milestone.
A4: Phase 2 | B4: Financial Management | C4: Purchasing, AP, GL, bank reconciliation, payroll/HR, approvals | D4: Financial and payroll workflows configured | E4: =SUM('Implementation Cost'!G11:G12)+'Implementation Cost'!G17 | F4: =E4*Assumptions!$B$3 | G4: =F4*Assumptions!$B$5 | H4: Accounting and security milestone.
A5: Phase 3 | B5: Reporting & Documents | C5: Documents, Sign, communications, portal, dashboards | D5: Dashboards, customer comms and documents live | E5: =SUM('Implementation Cost'!G13:G15) | F5: =E5*Assumptions!$B$3 | G5: =F5*Assumptions!$B$5 | H5: Portal/booking scope to confirm.
A6: Phase 4 | B6: Migration, QA & Go-Live | C6: Data migration, testing, training, cutover, stabilization | D6: Validated migration, UAT sign-off and go-live | E6: =SUM('Implementation Cost'!G16:G16)+SUM('Implementation Cost'!G18:G20) | F6: =E6*Assumptions!$B$3 | G6: =F6*Assumptions!$B$5 | H6: 30-day stabilization included.
D8: Subtotal by phases | E8: =SUM(E2:E6) | F8: =SUM(F2:F6) | G8: =SUM(G2:G6)

Sheet Risks
A1: # | B1: Risk | C1: Impact | D1: Probability | E1: Description | F1: Mitigation | G1: Status
A2: 1 | B2: Court scheduler fit | C2: High | D2: High | E2: Odoo does not provide a racquet-court scheduler exactly matching the BRD. | F2: Prototype in phase 0/1; freeze reservation rules early. | G2: Open
A3: 2 | B3: Membership privileges and family accounts | C3: High | D3: Medium | E3: Billing, family relationships and booking privileges can become complex. | F3: Create membership catalog and household examples before build. | G3: Open
A4: 3 | B4: US payroll compliance | C4: High | D4: Medium | E4: Payroll requirements may require US-specific provider or manual process. | F4: Confirm provider and legal compliance responsibility. | G4: Open
A5: 4 | B5: Sage 50/data migration quality | C5: High | D5: High | E5: Data quality may affect timeline and reconciliation. | F5: Request sample exports; run mock migration and cleansing. | G5: Open
A6: 5 | B6: POS hardware/payment terminal compatibility | C6: Medium | D6: Medium | E6: Hardware/provider choices affect POS setup. | F6: Confirm hardware list and processor before procurement. | G6: Open
A7: 6 | B7: Online booking scope creep | C7: High | D7: Medium | E7: Online booking can expand into website/app development. | F7: Decide phase 1 vs later and define member rules. | G7: Open
A8: 7 | B8: Financial reconciliation acceptance | C8: High | D8: Medium | E8: GL, AR, AP and inventory must reconcile before go-live. | F8: Define reconciliation owners and sign-off templates. | G8: Open
A9: 8 | B9: Custom development upgradeability | C9: Medium | D9: High | E9: Heavy custom code can affect future Odoo upgrades. | F9: Use configuration/Studio first and document custom modules. | G9: Open
A10: 9 | B10: User adoption at front desk | C10: Medium | D10: Medium | E10: Busy front-desk workflows need fast UX. | F10: Prototype check-in, POS and reservations with real users. | G10: Open
A11: 10 | B11: India/US time-zone coordination | C11: Medium | D11: Low | E11: Offshore delivery requires structured overlap. | F11: Set fixed overlap window and weekly governance. | G11: Open

Sheet Clarifications
A1: Area | B1: Question / Input Required
A2: User Count | B2: How many paid internal users are required at go-live by role?
A3: Courts | B3: How many courts, court types, operating hours and maintenance block rules are needed?
A4: Booking Rules | B4: What are member booking windows, cancellation rules, guest rules and override permissions?
A5: Online Booking | B5: Is online member court booking required in phase 1 or future phase?
A6: Memberships | B6: List all membership types, prices, billing cycles, privileges and family rules.
A7: Programs | B7: List lesson, clinic, league and tournament formats with pricing and scheduling rules.
A8: Instructor Pay | B8: How are instructor compensation, commissions and payroll calculations handled?
A9: Payroll Provider | B9: Which US payroll provider or compliance process will be used?
A10: Sage 50 | B10: What Sage 50 version/export formats are available for GL, AR/AP, vendors, customers and inventory?
A11: Data Volumes | B11: How many customers, members, vendors, SKUs, invoices, open balances and historical reservations exist?
A12: Payments | B12: Which payment processor and terminals will be used for POS and online payments?
... A21: Decision Makers | B21: Who signs off on accounting, operations, data migration and UAT?

Sheet Traceability
A1: Requirement ID | B1: Area | C1: Requirement Summary | D1: Fit Category | E1: Cost Treatment
A2: BR-CRM-001 | B2: CRM | C2: Duplicate customer verification | D2: Partial | E2: Included in estimate
A3: BR-CRM-002 | B3: CRM | C3: Contact updates across modules | D3: Partial | E3: Included in estimate
A4: BR-CRM-003 | B4: CRM | C4: Customer interaction history | D4: Partial | E4: Included in estimate
A5: BR-CRM-004 | B5: CRM | C5: Archive inactive customers | D5: Partial | E5: Included in estimate
A6: BR-CRM-005 | B6: Documents | C6: Customer documents/waivers/contracts | D6: Standard/Config | E6: Included in estimate
A7: BR-CRM-006 | B7: Memberships | C7: Recurring membership invoicing | D7: Partial | E7: Included in estimate
A8: BR-COURT-001 | B8: Court Scheduling | C8: Prevent double booking | D8: Custom-heavy | E8: Included in estimate
A9: BR-COURT-002 | B9: Court Scheduling | C9: Membership-based booking rules | D9: Custom-heavy | E9: Included in estimate
A10: BR-COURT-003 | B10: Court Scheduling | C10: Cancellation returns availability | D10: Custom-heavy | E10: Included in estimate
A11: BR-COURT-004 | B11: Court Scheduling | C11: Waitlist notifications | D11: Custom-heavy | E11: Included in estimate
A12: BR-COURT-005 | B12: Court Scheduling | C12: Maintenance/special-event closures | D12: Custom-heavy | E12: Included in estimate
... A38: BR-ACC-013 | B38: Payroll | C38: Payroll adjustment approvals | D38: Partial | E38: Included in estimate

Sheet Assumptions
A1: Assumption | B1: Value | C1: Notes
A2: India blended hourly rate USD | B2: 28 | C2: Editable
A3: Contingency % | B3: 0.1 | C3: Editable
A4: Planning paid users | B4: 12 | C4: Editable in License sheet too
A5: FX USD to INR | B5: 83.5 | C5: Editable planning assumption
A6: Delivery model | B6: Remote India delivery | C6: Onsite travel excluded
A9: Topic | B9: Assumption / Note
A10: Commercial note | B10: This is an India delivery planning estimate in USD with INR reference. It is not a binding quote.
A11: License note | B11: Odoo license is separate from implementation. Final quote should be obtained from Odoo or the selling partner based on billing country.
A12: Scope baseline | B12: The 72-page BRD is the baseline. Detailed discovery can change scope, hours and cost.
A13: Remote delivery | B13: Remote workshops and go-live support assumed. Onsite travel and expenses are excluded.
A14: Data | B14: Client must provide Sage 50/spreadsheet exports, field definitions and business validation owners.
A15: Custom code | B15: Custom development is last resort per BRD; custom modules must be documented and upgrade-safe.
A16: Support | B16: 30-day stabilization included; managed support after that is separate.

Sheet Sources
A1: Source | B1: URL / File | C1: Used For | D1: Notes
A2: BRD PDF | B2: Fox Cities Racquet Club - Odoo Business Requirements Document v1 (1).pdf | C2: Scope, requirements, roles, migration and acceptance criteria | D2: Downloaded from attached file and analyzed locally.
A3: Odoo pricing | B3: https://www.odoo.com/pricing | C3: Odoo plan structure, all-app subscription, paid-user rule and exclusions | D3: Final license quote to be confirmed with Odoo/Odoo partner.
A4: Odoo Success Packs | B4: https://www.odoo.com/pricing-packs | C4: Implementation benchmark and Odoo service scope reference | D4: Used as reference only; India partner estimate uses BRD workstreams.
