Workbook

Sheet Summary
A1: Fox Cities Racquet Club - BRD Implementation Cost Sheet
A2: Prepared from attached BRD/SOW dated 2026-07-17. Currency: USD. Summary shows implementation services only.
A4: Prepared for | B4: Fox Cities Racquet Club | D4: Cost Basis | E4: Attached BRD/SOW implementation scope
A5: Prospect address | B5: Fox Cities Racquet Club 2915 N. Victory Lane Appleton, WI 54913 | D5: Source | E5: foxcitiesracquetclub.com Location/Hours
A6: Phone | B6: 920.739.0221 | D6: Website | E6: https://www.foxcitiesracquetclub.com/
A7: Prepared date | B7: 2026-07-17 | D7: Implementation rate | E7: =Assumptions!B5
A8: Currency | B8: =Assumptions!B4 | D8: Contingency | E8: Removed
A10: Cost Summary | B10: Monthly Equivalent | C10: One-Time | D10: Notes
A11: Estimated implementation total | C11: ='Implementation Cost'!J21 | D11: Implementation services only; no contingency buffer included.
A14: Payment Terms
A15: Milestone | B15: Percentage | C15: Amount | D15: Notes
A16: Advance payment | B16: 0.5 | C16: =$C$11*B16 | D16: Due before project kickoff.
A17: On UAT | B17: 0.35 | C17: =$C$11*B17 | D17: Due on UAT readiness / UAT start.
A18: On go live | B18: 0.15 | C18: =$C$11*B18 | D18: Due on production go-live.
A19: Total | B19: =SUM(B16:B18) | C19: =SUM(C16:C18) | D19: Matches implementation total.
A22: Key Exclusions | B22: Hardware and IoT devices are not included. Any third-party connectivity will be studied and quoted separately.
A25: Implementation Scope Highlights
B26: Custom court booking configuration, dashboard validation, conflict prevention, lifecycle, no-show indicators and booking invoicing.
B27: Membership plans, membership year, prorated invoice wizard, member/non-member status and one-active-membership validation.
B28: Retail product, inventory, purchase, sales, POS and barcode setup for pro-shop operations.
B29: Accounting setup/validation for booking, membership, sales, POS and purchase flows.
B30: CRM stages/opportunities, reporting pack, UAT, training and handover.

Sheet Implementation Cost
A1: Implementation Cost Estimate - Attached BRD Scope
A2: Planning estimate only. Hardware, IoT devices, and third-party connectivity are excluded. Odoo subscription license remains on the separate license sheet and is not included in the implementation total.
A4: WBS | B4: Phase / Workstream | C4: BRD Reference | D4: Scope Included | E4: Odoo Apps / Components | F4: Low Hours | G4: Base Hours | H4: High Hours | I4: Rate | J4: Base Cost | K4: Risk | L4: Notes
A5: DISC | B5: Discovery and confirmation | C5: 15 Phase 1 | D5: Confirm courts, capacities, billing basis, operating hours, membership plans/prices/year, non-member fee, ball machine rate, product categories, POS payments and accounting mappings. | E5: Project, Knowledge | F5: 24 | G5: 32 | H5: 44 | I5: =Assumptions!$B$5 | J5: =G5*I5 | K5: Medium | L5: Includes configuration workbook, process maps and demo data list.
A6: PM | B6: Project management and governance | C6: All phases | D6: Status meetings, RAID/change control, schedule coordination, UAT tracking and delivery administration. | E6: Project | F6: 25 | G6: 35 | H6: 50 | I6: =Assumptions!$B$5 | J6: =G6*I6 | K6: Medium | L6: Remote governance assumed.
A7: BASE | B7: Base Odoo setup and access rights | C7: 1, 14, 15 | D7: Company settings, users, role/security baseline, apps readiness, email/basic system setup and standard module installation checks. | E7: Settings, Contacts, Discuss | F7: 18 | G7: 24 | H7: 34 | I7: =Assumptions!$B$5 | J7: =G7*I7 | K7: Low | L7: Does not include Odoo subscription or hosting fees.
A8: COURT | B8: Custom court booking configuration and validation | C8: 3, 4, 13.1, 13.2 | D8: Configure courts, seat capacity, person/hour vs court/hour policies, rates, dashboard availability, conflict prevention, lifecycle states, start/end rules, no-show indicators and reminders. | E8: Custom FCRC Court Seat Booking, Accounting, Product, Web, Mail | F8: 70 | G8: 95 | H8: 135 | I8: =Assumptions!$B$5 | J8: =G8*I8 | K8: High | L8: Main custom-risk area; assumes the core custom module already exists and is being configured/validated for this demo scope.
A9: MEM | B9: Membership configuration and invoicing | C9: 5 | D9: Membership years, plans, auto-created service products, proration rules, one-active-membership validation, member/non-member menus and booking pricing behavior. | E9: Contacts, Invoicing, Product, Custom membership models | F9: 38 | G9: 52 | H9: 74 | I9: =Assumptions!$B$5 | J9: =G9*I9 | K9: High | L9: Family eligibility automation is excluded per BRD.
A10: BILL | B10: Booking billing and accounting integration | C10: 4.8, 10, 15 Phase 4 | D10: Income account mapping, court invoice lines, non-member entry fees, ball machine lines, invoice smart button/linkage, draft invoice delete behavior, posted invoice controls and scheduled-hours billing validation. | E10: Accounting, Invoicing, Custom booking module | F10: 35 | G10: 48 | H10: 70 | I10: =Assumptions!$B$5 | J10: =G10*I10 | K10: High | L10: Tax and revenue-account mapping require client approval.
A11: INV | B11: Retail product and inventory setup | C11: 6, 15 Phase 5 | D11: Product categories, stockable retail products, SKU/barcode fields, sales/cost prices, initial quantities, vendors where available, reorder rules and stock availability review. | E11: Inventory, Product, Barcode | F11: 36 | G11: 50 | H11: 70 | I11: =Assumptions!$B$5 | J11: =G11*I11 | K11: Medium | L11: Physical inventory count and hardware are excluded.
A12: PUR | B12: Purchase setup | C12: 9, 15 Phase 6 | D12: Vendor setup, vendor prices, RFQ/PO workflow, receipts into stock, vendor bill creation and purchase-to-accounting validation. | E12: Purchase, Inventory, Accounting | F12: 18 | G12: 26 | H12: 38 | I12: =Assumptions!$B$5 | J12: =G12*I12 | K12: Medium | L12: Vendor catalog integration, if any, is separate.
A13: SALES | B13: Sales setup | C13: 7, 15 Phase 7 | D13: Sales quotation flow, retail product sales orders, sales order invoice validation, customer sales history and optional templates for group/corporate quotes. | E13: Sales, Invoicing, Contacts | F13: 16 | G13: 24 | H13: 34 | I13: =Assumptions!$B$5 | J13: =G13*I13 | K13: Low | L13: Event/group booking automation beyond quote flow is excluded.
A14: POS | B14: Point of Sale setup | C14: 8, 15 Phase 8 | D14: POS shop/session, POS product categories, retail product availability, payment methods, POS sale validation, inventory deduction and accounting entry generation. | E14: Point of Sale, Inventory, Accounting | F14: 24 | G14: 34 | H14: 50 | I14: =Assumptions!$B$5 | J14: =G14*I14 | K14: Medium | L14: Payment terminals and processor fees are excluded.
A15: BAR | B15: Barcode setup | C15: 11, 15 Phase 9 | D15: Barcode policy, barcode values on stockable products, scanning validation in POS, receipts and inventory adjustments, label-needs review. | E15: Barcode, Inventory, POS | F15: 14 | G15: 20 | H15: 30 | I15: =Assumptions!$B$5 | J15: =G15*I15 | K15: Medium | L15: Complex barcode label templates and scanners are excluded.
A16: CRM | B16: CRM setup | C16: 12, 15 Phase 10 | D16: CRM stages, lead sources, sample opportunities, lead-to-contact conversion, quote/membership follow-up process. | E16: CRM, Sales, Contacts | F16: 14 | G16: 20 | H16: 30 | I16: =Assumptions!$B$5 | J16: =G16*I16 | K16: Low | L16: Marketing automation/campaign spend is excluded.
... A19: TRN | B19: Training and handover | C19: 15 Phase 13 | D19: User training for court dashboard, booking lifecycle, membership invoicing, POS, inventory, purchase, accounting, CRM, reports; admin handover and basic guide. | E19: All implemented apps | F19: 16 | G19: 24 | H19: 34 | I19: =Assumptions!$B$5 | J19: =G19*I19 | K19: Low | L19: Remote training assumed.
I20: Implementation subtotal | J20: =SUM(J5:J19)
I21: Estimated implementation total | J21: =J20

Sheet Odoo License Cost
A1: Odoo License Cost - Separate Sheet
A2: License subscription estimate only. Implementation services, hardware, IoT, Odoo.sh/hosting, IAP/SMS credits, payment terminals and third-party connectivity are excluded.
A4: Input | B4: Value | C4: Notes
A5: Planning paid internal users | B5: =Assumptions!$B$7 | C5: Editable in Assumptions. BRD lists roles but not exact user count.
A6: Standard annual list/user/month USD | B6: 24.9 | C6: Comparison only; not recommended for custom module/Odoo.sh deployment.
A7: Standard monthly list/user/month USD | B7: 31.1 | C7: Comparison only.
A8: Custom annual list/user/month USD | B8: 37.4 | C8: Recommended planning rate for Custom plan.
A9: Custom monthly list/user/month USD | B9: 46.8 | C9: Month-to-month comparison only.
A11: Plan Scenario | B11: Included | C11: Billing | D11: Monthly Equivalent | E11: Annual Cost | F11: Recommended | G11: Notes
A12: Standard - annual list | B12: All apps, Odoo Online | C12: Annual | D12: =B5*B6 | E12: =D12*12 | F12: No | G12: Comparison only; no custom modules/Odoo.sh custom-code hosting.
A13: Standard - monthly list | B13: All apps, Odoo Online | C13: Monthly | D13: =B5*B7 | E13: =D13*12 | F13: No | G13: Comparison only.
A14: Custom - annual list | B14: All apps, Odoo Online/Odoo.sh/on-premise, Studio, Multi-Company, External API | C14: Annual | D14: =B5*B8 | E14: =D14*12 | F14: Yes | G14: Recommended for this BRD because the scope uses a custom court booking module and custom workflows.
A15: Custom - monthly list | B15: All apps, Custom plan | C15: Monthly | D15: =B5*B9 | E15: =D15*12 | F15: No | G15: Comparison only; annual billing is usually cheaper.
A17: License Notes | B17: Details
A18: Backend users | B18: Only internal/staff backend users are counted in this planning sheet; website/customer portal users are not treated as paid backend users.
A19: Official quote | B19: Final Odoo license cost must be confirmed by Odoo or the selling partner for the billing country and contract term.
A20: Separate from implementation | B20: Implementation estimate is on the Implementation Cost sheet and is not included here.

Sheet Assumptions
A1: Assumptions and Editable Inputs
A3: Assumption | B3: Value | C3: Notes
A4: Currency | B4: USD | C4: All implementation and license figures are shown in USD.
A5: Implementation hourly rate USD | B5: 28 | C5: Editable blended remote delivery planning rate.
A6: Contingency buffer | B6: Removed | C6: No contingency buffer is applied per customer request.
A7: Planning paid internal users | B7: 5 | C7: Editable. BRD lists roles but does not provide exact named users.
A8: Recommended Odoo plan | B8: Custom - annual billing | C8: Recommended because the BRD includes custom court booking module usage and custom/advanced configuration.
A9: License pricing basis | B9: Planning estimate | C9: Confirm final Odoo subscription quote with Odoo or selling partner before contract.
A10: Scope source | B10: fcrc_brd_scope_of_work.pdf dated 2026-07-17 | C10: Attached BRD/SOW is the scope baseline for this workbook.
A11: Delivery model | B11: Remote implementation | C11: Onsite travel and expenses are excluded.
A12: Data ownership | B12: Client-provided master data | C12: Court list, rates, memberships, products, vendors, taxes, accounts and opening quantities must be provided/approved by FCRC.
A13: Third-party connectivity | B13: Excluded | C13: Any third-party integration/connectivity will be studied and quoted separately.
A14: Hardware and IoT | B14: Excluded | C14: Barcode scanners, POS terminals, printers, payment terminals, court access/lighting IoT and networking hardware are not included.
A15: Post-go-live support | B15: 30-day stabilization included | C15: Managed support after stabilization is separate.

Sheet BRD Traceability
A1: BRD Traceability to Cost Lines
A3: BRD Section | B3: Scope Area | C3: Cost WBS | D3: Workbook Treatment
A4: 1-2 | B4: Executive summary and business objectives | C4: DISC, PM, BASE | D4: Included in discovery, base setup and governance.
A5: 3 | B5: Current custom module overview | C5: COURT | D5: Configured and validated as implementation scope; not priced as hardware or third-party.
A6: 4 | B6: Court booking requirements | C6: COURT, BILL, RPT, UAT | D6: Included for dashboard, lifecycle, validations, billing and reporting validation.
A7: 5 | B7: Membership requirements | C7: MEM, BILL, UAT, TRN | D7: Included for membership plans, year, invoicing and statuses.
A8: 6 | B8: Retail inventory requirements | C8: INV, BAR, POS | D8: Included for products, stock, reorder rules and barcode-ready product master.
A9: 7 | B9: Sales module scope | C9: SALES | D9: Included for quotations, sales orders, invoices and order history.
A10: 8 | B10: Point of Sale scope | C10: POS, BAR | D10: Included for POS setup and process validation; POS hardware/payment terminals excluded.
A11: 9 | B11: Purchase module scope | C11: PUR | D11: Included for vendor/RFQ/PO/receipt/vendor bill flow.
A12: 10 | B12: Accounting module scope | C12: BILL, BASE, UAT | D12: Included for invoices, payments, AR/AP, account mapping and standard reporting readiness.
A13: 11 | B13: Barcode scope | C13: BAR | D13: Included for barcode data and scan validation; scanners and complex label templates excluded.
A14: 12 | B14: CRM scope | C14: CRM | D14: Included for stages, sources, sample opportunities and conversion flow.
... A19: 17-20 | B19: Assumptions, acceptance, risks, next steps | C19: DISC, UAT, PM | D19: Reflected in assumptions, UAT and risk notes.

Sheet Exclusions & Notes
A1: Exclusions and Commercial Notes
A3: Category | B3: Included in Cost? | C3: Treatment | D3: Notes
A4: Hardware and IoT devices | B4: No | C4: Excluded | D4: Barcode scanners, receipt printers, cash drawers, POS terminals/tablets, label printers, payment terminals, court lighting/access control, networking and other IoT devices are not included.
A5: Third-party connectivity | B5: No | C5: Separate study and quote | D5: Any payment gateway, bank feed, vendor catalog, SMS/email service, external website, access control, Sage/legacy connectivity or API integration will be studied and quoted separately.
A6: Odoo license | B6: Separate sheet | C6: Estimated separately | D6: See Odoo License Cost sheet. License is not part of the implementation service total.
A7: Odoo.sh / hosting | B7: No | C7: Quote separately if required | D7: Hosting is not included in the implementation total or license sheet unless separately quoted.
A8: Online portal booking / website checkout | B8: No | C8: Out of scope | D8: Excluded by BRD section 16 unless separately approved.
A9: Payment gateway integration | B9: No | C9: Out of scope / separate quote | D9: Processor setup, payment terminals and transaction fees are excluded.
A10: Automated recurring membership billing | B10: No | C10: Out of scope | D10: Excluded by BRD section 16.
A11: Family member eligibility automation | B11: No | C11: Out of scope | D11: Family handling remains operational outside ERP for the demo per BRD.
A12: Advanced lessons, leagues and tournaments | B12: No | C12: Out of scope | D12: Advanced coaching/lesson scheduling and league/tournament management are excluded by BRD section 16.
A13: Payroll | B13: No | C13: Out of scope | D13: Not listed in current implementation scope and excluded from this cost sheet.
A14: Complex barcode label printing templates | B14: No | C14: Out of scope | D14: Basic barcode fields and scan validation are included; complex template design is excluded.
A15: Data migration beyond setup/demo data | B15: No | C15: Separate quote if needed | D15: The BRD focuses configuration/demo readiness. Historical transaction migration is not included unless separately scoped.
