Workbook

Sheet Summary
A1: Fox Cities Racquet Club - Odoo Cost Estimate
A3: Prepared from | B3: BRD PDF v1.0 | D3: BRD Scope Highlights
A4: Currency | B4: USD | D4: • Integrated ERP replacing disconnected systems and manual processes.
A5: Prepared Date | B5: 2026-07-17 | D5: • CRM/customer master with family/household relationships and document history.
A6: Recommended License Plan | B6: Odoo Custom - annual billing | D6: • Membership management with automated renewals and recurring billing.
A7: Planning Paid Users | B7: ='Odoo License Cost'!B2 | D7: • Court scheduling with conflict prevention, recurring bookings, maintenance blocks, waitlists, and utilization reporting.
A8: Implementation Rate | B8: ='Assumptions'!B3 | D8: • Programs, lessons, clinics, leagues, instructor scheduling, and attendance tracking.
D9: • POS with barcode scanning, member pricing, gift cards, returns, payments, and immediate inventory/accounting posting.
A10: Cost Summary | D10: • Inventory/purchasing/vendor management with receiving, valuation, and AP matching.
A11: Implementation subtotal | B11: ='Implementation Cost'!K22 | D11: • Accounting, payroll/HR, role-based security, dashboards, migration, UAT, cutover, and 30-day stabilization.
A12: Implementation contingency | B12: ='Implementation Cost'!K23
A13: Implementation total | B13: ='Implementation Cost'!K24
A14: Recommended Odoo license, year 1 | B14: ='Odoo License Cost'!E13 | D14: Recommendation
A15: Estimated hardware/third-party, upfront | B15: ='Hardware & Third Party'!E16 | D15: Use Odoo Custom plan for costing because the BRD includes custom workflows, Odoo Studio/custom modules, external integrations/API possibility, portal/online booking readiness, and role/security customization. The implementation estimate follows the BRD configuration-first principle and treats custom development as last resort.
A16: Estimated first-year total | B16: =B13+B14+B15
A17: Estimated recurring annual license only | B17: ='Odoo License Cost'!E13

Sheet Implementation Cost
A1: WBS | B1: Workstream | C1: BRD Coverage | D1: Scope Included | E1: Odoo Apps / Components | F1: Low Hours | G1: Base Hours | H1: High Hours | I1: Risk | J1: Notes | K1: Base Cost
A2: DISC | B2: Discovery, BRD validation & solution blueprint | C2: All sections | D2: Process workshops, fit-gap, requirements traceability, solution design, backlog, project plan | E2: Project, Knowledge | F2: 60 | G2: 90 | H2: 120 | I2: Medium | J2: Includes validation of 72-page BRD and configuration-first design. | K2: =G2*Assumptions!$B$3
A3: PM | B3: Project management & governance | C3: All workstreams | D3: Status meetings, RAID log, change control, steering reviews, budget/schedule management | E3: Project | F3: 55 | G3: 80 | H3: 110 | I3: Medium | J3: Assumes remote project governance. | K3: =G3*Assumptions!$B$3
A4: BASE | B4: Base Odoo setup & environment configuration | C4: NFR, Security, Maintainability | D4: Company setup, fiscal settings, users, email templates, system parameters, backup/cutover settings | E4: Settings, Discuss, Documents | F4: 35 | G4: 50 | H4: 70 | I4: Low | J4: Odoo.sh/on-prem hosting excluded unless selected. | K4: =G4*Assumptions!$B$3
A5: CRM | B5: CRM, customer records & family relationships | C5: BR-CRM-001 to BR-CRM-005 | D5: Customer master, duplicate controls, household/family links, archive rules, customer history, communications, documents | E5: CRM, Contacts, Documents, Email Marketing | F5: 95 | G5: 135 | H5: 180 | I5: High | J5: Family/household logic may require custom fields and views. | K5: =G5*Assumptions!$B$3
A6: MEM | B6: Membership management & recurring billing | C6: BR-CRM-006, Membership scope | D6: Membership types, privileges, annual/monthly billing, renewals, guest handling, customer balances, statements | E6: Subscriptions, Invoicing, Sales | F6: 90 | G6: 130 | H6: 175 | I6: High | J6: Assumes membership billing mapped to subscriptions/recurring invoices. | K6: =G6*Assumptions!$B$3
A7: COURT | B7: Court scheduling & reservations | C7: BR-COURT-001 to BR-COURT-006 | D7: Courts/resources, reservation calendar, recurring bookings, booking windows, conflict prevention, maintenance blocks, waitlists | E7: Appointments, Planning, Calendar, Website/Portal | F7: 170 | G7: 240 | H7: 330 | I7: High | J7: Largest custom-risk area; Odoo has no out-of-box racquet court scheduler. | K7: =G7*Assumptions!$B$3
A8: PROG | B8: Programs, instruction, lessons, clinics & leagues | C8: Programs and Instruction scope | D8: Private/group lessons, clinics, junior/adult programs, league administration, attendance, instructor assignment | E8: Planning, Events, Sales, Project | F8: 110 | G8: 155 | H8: 220 | I8: High | J8: League scheduling and attendance rules may need custom configuration. | K8: =G8*Assumptions!$B$3
A9: POS | B9: Point of Sale retail operations | C9: BR-POS-001 to BR-POS-006 | D9: POS setup, barcode scanning, member pricing, discounts, gift cards, returns/exchanges, payment flow, customer purchase history | E9: POS, Sales, Payments | F9: 75 | G9: 105 | H9: 145 | I9: Medium | J9: Payment terminal provider setup excluded from license cost. | K9: =G9*Assumptions!$B$3
A10: INV | B10: Inventory & purchasing | C10: BR-INV-001 to BR-INV-006 | D10: Products, SKUs, stock locations, receiving, adjustments, valuation, reorder rules, purchase orders, vendor bills match | E10: Inventory, Purchase, Barcode, Accounting | F10: 95 | G10: 135 | H10: 185 | I10: Medium | J10: Includes retail, teaching, office, and maintenance inventory categories. | K10: =G10*Assumptions!$B$3
A11: ACC | B11: Accounting, AR/AP, GL & bank reconciliation | C11: BR-ACC-001 to BR-ACC-009 | D11: Chart of accounts, AR/AP, customer invoices, payments, reminders, vendor bills, approvals, bank reconciliation, financial statements | E11: Accounting, Invoicing, Approvals | F11: 120 | G11: 165 | H11: 230 | I11: High | J11: Sage 50 reconciliation and opening balances included in migration rows. | K11: =G11*Assumptions!$B$3
A12: PAY | B12: Payroll & HR | C12: BR-ACC-010 to BR-ACC-013 | D12: Employee records, payroll rules, leave balances, payroll approval, GL posting, payroll reporting | E12: Employees, Payroll, Time Off, Approvals | F12: 70 | G12: 105 | H12: 155 | I12: High | J12: US payroll localization/provider dependency may change scope. | K12: =G12*Assumptions!$B$3
A13: DOC | B13: Documents, waivers, contracts & e-signature | C13: BR-CRM-005, Documentation | D13: Document folders, waivers/contracts, attachment rules, document history, e-sign workflow where applicable | E13: Documents, Sign, Contacts | F13: 45 | G13: 70 | H13: 100 | I13: Medium | J13: Assumes standard Odoo Sign where possible. | K13: =G13*Assumptions!$B$3
... A20: GO | B20: Cutover, go-live & 30-day stabilization | C20: Cutover Strategy, Overall Acceptance | D20: Go-live checklist, final migration, freeze window, contingency plan, launch support, 30-day stabilization | E20: All modules | F20: 70 | G20: 105 | H20: 150 | I20: High | J20: Includes post-go-live support window. | K20: =G20*Assumptions!$B$3
J22: Implementation subtotal | K22: =SUM(K2:K20)
J23: Contingency | K23: =K22*Assumptions!$B$4
J24: Implementation total | K24: =K22+K23

Sheet Odoo License Cost
A1: Odoo License Cost - USD
A2: Planning paid internal users | B2: 12 | C2: Editable. BRD lists roles but not exact headcount. Customer/member portal users are not paid users.
A3: Standard annual billing price per user/month | B3: 24.9 | C3: USD, annual billing list rate used for planning.
A4: Standard monthly billing price per user/month | B4: 31.1 | C4: USD, month-to-month rate used for comparison.
A5: Custom annual billing price per user/month | B5: 37.4 | C5: USD, annual billing list rate used for recommendation.
A6: Custom monthly billing price per user/month | B6: 46.8 | C6: USD, month-to-month rate used for comparison.
A9: Plan Scenario | B9: Included | C9: Billing | D9: Monthly Cost | E9: Annual Cost | F9: Notes
A10: One App Free | B10: One app, unlimited users, Odoo Online | C10: N/A | D10: =0 | E10: =0 | F10: Not suitable for BRD because multiple apps are required.
A11: Standard | B11: All apps, Odoo Online | C11: Annual billing | D11: =B2*B3 | E11: =D11*12 | F11: Comparison only; not recommended if custom modules/API/Studio are required.
A12: Standard | B12: All apps, Odoo Online | C12: Monthly billing | D12: =B2*B4 | E12: =D12*12 | F12: Comparison only.
A13: Custom - Recommended | B13: All apps, Odoo Online/Odoo.sh/on-premise, Studio, Multi-Company, External API | C13: Annual billing | D13: =B2*B5 | E13: =D13*12 | F13: Recommended for BRD because custom workflows, integrations and Odoo Studio/custom development are likely.
A14: Custom | B14: All apps, Odoo Online/Odoo.sh/on-premise, Studio, Multi-Company, External API | C14: Monthly billing | D14: =B2*B6 | E14: =D14*12 | F14: Comparison only.
A15: Odoo.sh hosting | B15: Continuous integration hosting for custom modules | C15: Quote required | D15: =0 | E15: =0 | F15: Not included in Odoo license cost; add once hosting decision is made.
A18: License Notes
A19: • Official Odoo pricing page states Standard and Custom include all apps for a single fee and all plans include support, hosting and maintenance.
A20: • Odoo pricing page notes implementation services, in-app purchase credits, Odoo.sh hosting for custom developments, and custom code maintenance are not included in license pricing.
A21: • Paid users are internal users accessing backend records. Customer/member portal users are not included as paid users per Odoo pricing FAQ.
A22: • Final subscription quote should be validated with Odoo/Odoo partner before contract signature because pricing and region/currency can change.

Sheet Hardware & Third Party
A1: Category | B1: Item | C1: Qty | D1: Unit Cost USD | E1: Estimated Cost | F1: Notes
A2: POS Hardware | B2: Barcode scanners | C2: 2 | D2: 175 | E2: =C2*D2 | F2: Needed for BR-POS-001. Final model depends on POS device.
A3: POS Hardware | B3: Receipt printers | C3: 2 | D3: 300 | E3: =C3*D3 | F3: Estimate only.
A4: POS Hardware | B4: Cash drawers | C4: 2 | D4: 150 | E4: =C4*D4 | F4: Estimate only.
A5: POS Hardware | B5: Label printer for inventory/barcodes | C5: 1 | D5: 450 | E5: =C5*D5 | F5: Useful for inventory SKU/barcode labels.
A6: POS Hardware | B6: POS terminal/tablet/computer allowance | C6: 2 | D6: 850 | E6: =C6*D6 | F6: Use existing hardware if compatible.
A7: Payments | B7: Payment terminals | C7: 2 | D7: 0 | E7: =C7*D7 | F7: Processor/provider quote required; not included.
A8: Communications | B8: SMS / IAP credits | C8: 1 | D8: 0 | E8: =C8*D8 | F8: Odoo in-app purchase credits excluded from license.
A9: Payroll | B9: US payroll provider/subscription | C9: 1 | D9: 0 | E9: =C9*D9 | F9: Provider cost and compliance model to be confirmed.
A10: Data | B10: Sage 50 export/support assistance | C10: 1 | D10: 0 | E10: =C10*D10 | F10: May be handled by client or vendor.
A11: Travel | B11: Onsite travel and expenses | C11: 1 | D11: 0 | E11: =C11*D11 | F11: Remote implementation assumed. Add if onsite required.
A12: Contingency | B12: Hardware contingency | C12: 1 | D12: =SUM(E2:E11)*0.10 | E12: =C12*D12 | F12: 10% hardware contingency.
D16: Total | E16: =SUM(E2:E12)

Sheet Phasing
A1: Phase | B1: BRD Priority | C1: Workstreams | D1: Target Outcome | E1: Estimated Base Hours | F1: Estimated Cost | G1: Notes
A2: Phase 0 | B2: Initiation | C2: Discovery, blueprint, project governance, base setup | D2: Validated solution design, backlog, environment readiness | E2: =SUM('Implementation Cost'!G2:G4) | F2: =E2*Assumptions!$B$3 | G2: Before configuration build.
A3: Phase 1 | B3: Core Operations | C3: CRM, memberships, court scheduling, programs, POS, inventory, AR/customer billing | D3: Front desk and daily operational workflows ready for UAT | E3: =SUM('Implementation Cost'!G5:G10) | F3: =E3*Assumptions!$B$3 | G3: Matches BRD Phase 1 core operations.
A4: Phase 2 | B4: Financial Management | C4: Purchasing, AP, GL, bank reconciliation, payroll/HR, approvals | D4: Financial workflows and payroll/HR aligned to accounting close | E4: =SUM('Implementation Cost'!G11:G12)+'Implementation Cost'!G17 | F4: =E4*Assumptions!$B$3 | G4: Matches BRD Phase 2 and security requirements.
A5: Phase 3 | B5: Reporting & Documents | C5: Documents, Sign, communications, portal, dashboards, reports | D5: Management visibility and customer-facing communication flows | E5: =SUM('Implementation Cost'!G13:G15) | F5: =E5*Assumptions!$B$3 | G5: Includes optional online booking readiness.
A6: Phase 4 | B6: Migration, QA & Go-Live | C6: Data migration, testing, training, cutover, stabilization | D6: Validated migration, UAT acceptance, go-live, 30-day stabilization | E6: =SUM('Implementation Cost'!G16:G16)+SUM('Implementation Cost'!G18:G20) | F6: =E6*Assumptions!$B$3 | G6: Final acceptance criteria and cutover.
D8: Subtotal by phases | E8: =SUM(E2:E6) | F8: =SUM(F2:F6)

Sheet Assumptions
A1: Assumptions and Exclusions
A3: Implementation hourly rate USD | B3: 95 | C3: Editable
A4: Implementation contingency % | B4: 0.1 | C4: Editable
A5: Paid internal users | B5: 12 | C5: Editable in Odoo License Cost sheet
A8: Key Assumptions
A9: • The BRD is used as the pricing scope baseline; detailed fit-gap may change estimates.
A10: • Configuration-first approach is assumed; custom development is limited to gaps not covered by standard Odoo, Studio, or supported modules.
A11: • 12 paid internal users are assumed because the BRD defines roles but not exact staff count. Customer/member portal users are assumed free under Odoo pricing rules.
A12: • Odoo Custom annual plan is recommended for budgeting due to custom modules/workflows, Odoo Studio/customization, API/integration possibility, and future online booking requirements.
A13: • US payroll feasibility depends on chosen payroll method/provider and compliance requirements.
A14: • Payment processor/terminal costs, SMS/IAP credits, Odoo.sh hosting, custom-code maintenance, and onsite travel are excluded unless explicitly added.
A15: • Data migration estimate assumes client supplies usable Sage 50 exports, spreadsheets, and cleansed source files in agreed formats.
A16: • Hardware estimates are placeholders and should be validated against selected POS devices and payment processor.
A17: • All amounts are in USD and are planning estimates, not a binding quotation.
A22: Out of Scope Unless Added by Change Order
A23: • Website redesign/redevelopment beyond standard Odoo portal/website setup.
... A28: • Ongoing managed support after 30-day stabilization unless contracted separately.

Sheet Sources
A1: Source | B1: URL / File | C1: Used For | D1: Notes
A2: BRD PDF | B2: Fox Cities Racquet Club - Odoo Business Requirements Document v1 (1).pdf | C2: Implementation scope, workstreams, migration, roles, acceptance criteria | D2: Downloaded from attached signed URL on 2026-07-17.
A3: Odoo Pricing | B3: https://www.odoo.com/pricing | C3: Plan inclusions, all-app pricing model, plan limitations/exclusions, paid user rule | D3: USD license rates used in workbook: Standard $24.90/$31.10 and Custom $37.40/$46.80 per user/month for annual/monthly billing. Confirm final quote with Odoo/partner.
A4: Odoo Success Packs | B4: https://www.odoo.com/pricing-packs | C4: Benchmark reference for implementation activities and Odoo service exclusions | D4: Used as reference only; this workbook uses partner-style workstream estimate.
