Workbook

Sheet Summary
A1: Fox Cities Racquet Club - Odoo Meeting Cost Estimate
A2: Prepared from July 15, 2026 meeting notes and available BRD scope. Currency: USD.
A4: Prepared for | B4: Fox Cities Racquet Club | D4: Recommended Direction
A5: Prospect contact | B5: Dean Verstegen | D5: Use Odoo Custom with Odoo.sh because the meeting includes custom court dashboard work and custom modules. Odoo.sh hosting is separate from the license.
A6: Prepared date | B6: 2026-07-17 | D6: Current paid users | E6: 5
A7: Currency | B7: USD | D7: Implementation model | E7: Remote hourly estimate
A8: Planning hourly rate | B8: ='Assumptions'!B3 | D8: Odoo.sh baseline | E8: 1 worker, 50 GB storage, 1 staging env
A10: Cost Summary - Meeting MVP
A11: Line Item | B11: Monthly Equivalent | C11: Annual / One-Time | D11: Notes
A12: Implementation subtotal | C12: ='Implementation Cost'!J20 | D12: Base-hour estimate before contingency.
A13: Implementation contingency | C13: ='Implementation Cost'!J21 | D13: 15% planning contingency.
A14: Implementation total | C14: ='Implementation Cost'!J22 | D14: One-time implementation budget for meeting MVP.
A15: Odoo Custom license - first-year promo | B15: ='Odoo License & Hosting'!D15 | C15: ='Odoo License & Hosting'!E15 | D15: 5 paid users, annual billing monthly equivalent.
A16: Odoo Custom license - renewal/list | B16: ='Odoo License & Hosting'!D16 | C16: ='Odoo License & Hosting'!E16 | D16: Conservative recurring budget after first-year discount period.
A17: Odoo.sh hosting - with staging | B17: ='Odoo License & Hosting'!D24 | C17: ='Odoo License & Hosting'!E24 | D17: 1 worker + 50 GB + 1 staging environment.
A18: Estimated first-year total - promo license | B18: ='Odoo License & Hosting'!D15+'Odoo License & Hosting'!D24 | C18: =C14+C15+C17 | D18: Implementation + first-year discounted license + Odoo.sh hosting.
A19: Estimated first-year total - list license | B19: ='Odoo License & Hosting'!D16+'Odoo License & Hosting'!D24 | C19: =C14+C16+C17 | D19: Same implementation scope using list/renewal license price.
A20: Recurring annual license + hosting after year 1 | B20: ='Odoo License & Hosting'!D16+'Odoo License & Hosting'!D24 | C20: =C16+C17 | D20: Odoo Custom renewal/list license + Odoo.sh hosting only; excludes implementation and optional support.
A23: Meeting Scope Highlights
A24: Court booking with hourly rates, ball machine, start/end controls, 15-minute validation buffer, seasonal rates, and non-member booking limits.
A25: Custom court dashboard modeled after current court sheets/Excel workflow, pending high-resolution court-sheet images from Dean.
A26: Membership plans with prorated billing, member vs non-member logic, invoices, payments, and account balances.
A27: POS retail setup with products enabled for POS by default, barcode flow, cash closing, gift cards, coupons, and member pricing readiness.
A28: Accounting, bank/payment provider integration, purchase orders, inventory reporting, and optional Odoo website replacement.

Sheet Implementation Cost
A1: Meeting-Based Implementation Estimate
A2: Editable hourly rate and contingency are on the Assumptions sheet. This is a planning estimate, not a fixed quote.
A4: WBS | B4: Workstream | C4: Meeting Requirement | D4: Scope Included | E4: Odoo Apps / Components | F4: Low Hours | G4: Base Hours | H4: High Hours | I4: Rate | J4: Base Cost | K4: Risk | L4: Notes
A5: DISC | B5: Discovery, BRD validation & solution blueprint | C5: Review 72-page BRD; confirm board-priority scope | D5: Fit-gap workshops, current workflow review, implementation backlog, phase plan | E5: Project, Knowledge | F5: 30 | G5: 45 | H5: 65 | I5: ='Assumptions'!$B$3 | J5: =G5*I5 | K5: Medium | L5: Required before final fixed-price commitment.
A6: PM | B6: Project management & governance | C6: Board proposal and contract initiation | D6: Status meetings, RAID log, change control, budget and schedule tracking | E6: Project | F6: 25 | G6: 40 | H6: 60 | I6: ='Assumptions'!$B$3 | J6: =G6*I6 | K6: Medium | L6: Remote governance assumed.
A7: BASE | B7: Odoo.sh/base environment setup | C7: US localization, users, settings, email | D7: Company setup, users/security baseline, mail, technical settings, Odoo.sh repo/deployment readiness | E7: Settings, Discuss, Odoo.sh | F7: 25 | G7: 35 | H7: 50 | I7: ='Assumptions'!$B$3 | J7: =G7*I7 | K7: Low | L7: License/hosting costs are separate.
A8: ACC | B8: Accounting, invoicing, payments & bank setup | C8: Accounting demo, Sage chart mapping, payment providers | D8: US localization, journals, taxes, payment terms, bank sync readiness, payment provider setup, invoice/payment workflow | E8: Accounting, Invoicing, Payments | F8: 40 | G8: 60 | H8: 90 | I8: ='Assumptions'!$B$3 | J8: =G8*I8 | K8: High | L8: Sage migration depth can change cost.
A9: MEM | B9: Membership plans & prorated billing | C9: Adult/family plans, prorated invoices, member/non-member | D9: Membership products, recurring/prorated billing, member status logic, invoices, payments, balances | E9: Subscriptions, Sales, Invoicing | F9: 45 | G9: 70 | H9: 105 | I9: ='Assumptions'!$B$3 | J9: =G9*I9 | K9: High | L9: Privilege rules should be confirmed in fit-gap.
A10: COURT | B10: Court booking configuration | C10: $28 court rate, ball machine, seasonal rates, limits | D10: Courts/resources, time slots, capacity, seasonal pricing, 15-minute validation buffer, non-member annual limit, booking-to-invoice flow | E10: Appointments, Calendar, Sales | F10: 70 | G10: 110 | H10: 165 | I10: ='Assumptions'!$B$3 | J10: =G10*I10 | K10: High | L10: Reservation rules are the main business-critical area.
A11: DASH | B11: Custom court sheet dashboard | C11: Interactive dashboard modeled on current Excel/paper sheet | D11: Daily court grid, court/time view, booking status, staff actions, start/end play flow, billing handoff | E11: Custom Odoo module, OWL/views | F11: 90 | G11: 140 | H11: 220 | I11: ='Assumptions'!$B$3 | J11: =G11*I11 | K11: High | L11: Needs HD current court-sheet images before final sizing.
A12: POS | B12: Point of Sale retail workflow | C12: Products available in POS by default; gifts/coupons | D12: POS shop setup, product default enablement, barcode flow, cash register closing, coupons, gift cards, member pricing readiness | E12: POS, Barcode, Loyalty | F12: 30 | G12: 50 | H12: 75 | I12: ='Assumptions'!$B$3 | J12: =G12*I12 | K12: Medium | L12: Payment terminal hardware/fees excluded.
A13: INV | B13: Inventory & purchasing | C13: Purchase orders, stock and forecast reporting | D13: Products/SKUs, stock locations, vendor records, purchase orders, receipts, basic inventory reports | E13: Inventory, Purchase | F13: 25 | G13: 45 | H13: 70 | I13: ='Assumptions'!$B$3 | J13: =G13*I13 | K13: Medium | L13: Assumes clean product/vendor list.
A14: WEB | B14: Website and portal foundation | C14: Replace outdated website if requested | D14: Basic Odoo website structure, member-facing pages, portal readiness, contact/forms content migration | E14: Website, Portal | F14: 35 | G14: 60 | H14: 95 | I14: ='Assumptions'!$B$3 | J14: =G14*I14 | K14: Medium | L14: Full marketing redesign or custom theme can be quoted separately.
A15: DATA | B15: Data import and migration | C15: Current data, Sage/spreadsheets, members/products | D15: Customer/member import, products, vendors, chart/opening balances, data validation support | E15: Import tools, Accounting, Contacts | F15: 45 | G15: 70 | H15: 120 | I15: ='Assumptions'!$B$3 | J15: =G15*I15 | K15: High | L15: Depends heavily on source export quality.
A16: RPT | B16: Dashboards and reporting | C16: Board visibility and operational reporting | D16: Court utilization, membership KPIs, POS sales, inventory, accounting reports, saved filters | E16: Dashboards, Spreadsheet BI | F16: 25 | G16: 45 | H16: 80 | I16: ='Assumptions'!$B$3 | J16: =G16*I16 | K16: Medium | L16: KPI definitions to be confirmed.
... A18: SUP | B18: 30-day stabilization support | C18: Support after launch | D18: Post-go-live support, minor fixes, workflow tuning, admin handover | E18: All modules | F18: 30 | G18: 45 | H18: 70 | I18: ='Assumptions'!$B$3 | J18: =G18*I18 | K18: Medium | L18: Ongoing managed support is separate.
I20: Implementation subtotal | J20: =SUM(J5:J18)
I21: Contingency | J21: =J20*'Assumptions'!$B$4
I22: Implementation total | J22: =J20+J21

Sheet Odoo License & Hosting
A1: Odoo License and Odoo.sh Hosting - USD
A2: Uses 5 paid internal users. Portal/customer users are not counted as paid backend users.
A4: Input | B4: Value | C4: Notes
A5: Paid internal users | B5: 5 | C5: User request. Member/customer portal users are assumed free.
A6: Standard annual first-year promo/user/month | B6: 19.9 | C6: Comparison only; annual billing monthly equivalent.
A7: Standard annual list/user/month | B7: 24.9 | C7: Comparison only.
A8: Custom annual first-year promo/user/month | B8: 29.9 | C8: Recommended first-year price if current discount applies.
A9: Custom annual list/user/month | B9: 37.4 | C9: Recommended conservative/renewal price.
A10: Custom monthly list/user/month | B10: 46.8 | C10: Month-to-month comparison.
A12: Plan Scenario | B12: Included | C12: Billing | D12: Monthly Equivalent | E12: Annual Cost | F12: Notes
A13: Standard - first-year promo | B13: All apps, Odoo Online | C13: Annual | D13: =$B$5*$B$6 | E13: =D13*12 | F13: Comparison only; not suitable for custom Python modules on Odoo.sh.
A14: Standard - annual list | B14: All apps, Odoo Online | C14: Annual | D14: =$B$5*$B$7 | E14: =D14*12 | F14: Comparison only.
A15: Custom - first-year promo | B15: All apps, Odoo Online/Odoo.sh/on-premise, Studio, Multi-Company, External API | C15: Annual | D15: =$B$5*$B$8 | E15: =D15*12 | F15: Recommended for year-1 budgeting if current promotion applies.
A16: Custom - annual list/renewal | B16: All apps, Odoo Online/Odoo.sh/on-premise, Studio, Multi-Company, External API | C16: Annual | D16: =$B$5*$B$9 | E16: =D16*12 | F16: Recommended conservative budget and recurring renewal planning.
A17: Custom - monthly list | B17: All apps, Custom plan | C17: Monthly | D17: =$B$5*$B$10 | E17: =D17*12 | F17: Comparison only.
A20: Odoo.sh Component | B20: Qty | C20: Unit Price / Month | D20: Monthly Equivalent | E20: Annual Cost | F20: Notes
A21: Worker | B21: 1 | C21: 57.6 | D21: =B21*C21 | E21: =D21*12 | F21: Annual billing monthly equivalent. Shared hosting baseline.
A22: Storage (GB) | B22: 50 | C22: 0.2 | D22: =B22*C22 | E22: =D22*12 | F22: 50 GB matches meeting estimate basis.
A23: Staging environment | B23: 1 | C23: 14.4 | D23: =B23*C23 | E23: =D23*12 | F23: Recommended for testing custom court dashboard changes.
A24: Odoo.sh total with staging | D24: =SUM(D21:D23) | E24: =SUM(E21:E23) | F24: This does not include the Odoo Enterprise license.
A25: Odoo.sh total without staging | D25: =D21+D22 | E25: =E21+E22 | F25: Matches the approximate $811/year figure discussed in the meeting.
A29: License and Hosting Notes
A30: Odoo.sh is separate from the Enterprise license. The Odoo.sh hosting price does not include the Odoo Enterprise license.
A31: Custom plan is recommended because Odoo.sh/custom Python modules and external API/customization needs are in scope.
A32: Current Odoo first-year discounts can change; use the list/renewal price for conservative board budgeting.
A33: The Odoo.sh worker/storage/staging numbers should be rechecked before contract signature and increased if public online booking traffic grows.

Sheet Full BRD Expansion
A1: Full BRD Expansion Budget Guide
A2: Optional view if the complete 72-page BRD is implemented as a larger program rather than only the meeting MVP.
A4: Scenario | B4: Low Hours | C4: Base Hours | D4: High Hours | E4: Low Cost | F4: Base Cost | G4: High Cost | H4: Notes
A5: Full BRD implementation | B5: 1575 | C5: 2275 | D5: 3200 | E5: =B5*'Assumptions'!$B$3 | F5: =C5*'Assumptions'!$B$3 | G5: =D5*'Assumptions'!$B$3 | H5: Based on the available BRD review estimate in the workspace.
A6: Contingency | E6: =E5*'Assumptions'!$B$4 | F6: =F5*'Assumptions'!$B$4 | G6: =G5*'Assumptions'!$B$4 | H6: Planning contingency.
A7: Full BRD implementation total | E7: =E5+E6 | F7: =F5+F6 | G7: =G5+G6 | H7: Implementation only; excludes license, Odoo.sh, hardware, processor fees, SMS credits, and post-stabilization support.
A8: Full BRD first-year total - base | F8: =F7+'Odoo License & Hosting'!E15+'Odoo License & Hosting'!E24 | H8: Base implementation + Custom first-year promo license + Odoo.sh with staging.
A11: Full BRD Workstreams Included
A12: CRM/customer master, household/family relationships, documents and customer communication history.
A13: Membership management, recurring billing, statements, guest/non-member privileges, and portal readiness.
A14: Court scheduling, programs/lessons/clinics/leagues, instructor scheduling, waitlists, utilization analytics.
A15: POS, barcode, gift cards/coupons, inventory, purchasing, accounting, Sage data migration, reports, roles and approvals.
A16: Payroll/HR scope remains dependent on selected US payroll provider/compliance approach.

Sheet Meeting Scope
A1: Meeting Notes - Requirements Used for Estimate
A2: Extracted from the downloaded Gemini notes and aligned to the available BRD.
A4: Area | B4: Meeting Requirement | C4: Costing Interpretation | D4: Priority
A5: Court booking | B5: $28 hourly court rate; full court or per-seat booking; start/end play cycle; 15-minute buffer validation. | C5: Configure court resources, booking products, validation rules, and billing handoff. | D5: High
A6: Custom dashboard | B6: Interactive court scheduling dashboard modeled after current Excel/court sheet. | C6: Custom module/dashboard is the highest-risk build item and requires current sheet images. | D6: High
A7: Membership | B7: Adult/family membership plans, prorated billing, members vs non-members, annual non-member booking limit. | C7: Configure plans, recurring/prorated invoices, membership status, and booking privileges. | D7: High
A8: POS | B8: Products should default to available in POS; barcode, cash payments, closing, gift cards and coupons demonstrated. | C8: Configure POS and small customization/automation for product POS availability defaults. | D8: Medium
A9: Accounting | B9: US localization/USD, invoices, bills, bank integration, PayPal/payment provider, Sage chart migration discussion. | C9: Accounting setup, payment provider config, CoA/Sage mapping, reconciliation workflow. | D9: High
A10: Inventory/Purchase | B10: Purchase quotations, vendors, product tracking, free stock and forecast reporting. | C10: Product/vendor setup, purchase flow, receiving, stock rules, reports. | D10: Medium
A11: Website | B11: Existing site is outdated and current hosting is about $12/month; Odoo website may replace it if requested. | C11: Include foundation-level Odoo website/portal setup; full redesign remains optional. | D11: Medium
A12: Hosting | B12: Odoo.sh and Deploy ERP discussed; request specifically asks for Odoo.sh pricing. | C12: Use Odoo.sh shared hosting estimate: 1 worker, 50GB, 1 staging env. | D12: High
A13: Engagement | B13: Hourly billing package vs fixed price discussed; board needs ballpark estimate. | C13: Workbook uses editable hourly-rate planning estimate; fixed price requires final scope sign-off. | D13: High

Sheet Assumptions
A1: Assumptions and Exclusions
A2: Edit the rate, contingency, users, and hosting quantities to revise totals.
A4: Assumption | B4: Value | C4: Notes
A5: Currency | B5: USD | C5: All amounts are shown in USD.
A6: Implementation hourly rate USD | B6: 28 | C6: Editable planning rate based on remote delivery. Update this cell to change implementation totals.
A7: Implementation contingency % | B7: 0.15 | C7: Editable contingency for unknowns, fit-gap, data quality, and custom dashboard risk.
A8: Paid internal users | B8: 5 | C8: User request. Customer/member portal users are excluded from paid backend user count.
A9: Recommended Odoo plan | B9: Custom - annual billing | C9: Needed for Odoo.sh/custom modules, Studio-style customization, multi-company/API availability.
A10: Odoo.sh baseline | B10: 1 worker, 50 GB, 1 staging | C10: Shared hosting estimate for small internal team and testing custom code. Scale if public traffic grows.
A11: Quote type | B11: Planning estimate | C11: Not a binding quote. Fixed price needs signed scope, sample data, and HD court sheet images.
A12: Scope source | B12: Meeting notes + available BRD | C12: Meeting notes drive MVP; full BRD tab shows broader program budget.
A13: Website | B13: Foundation only | C13: Full brand redesign, copywriting, custom theme, SEO campaign, and media production are excluded unless added.
A14: Payment/SMS/IAP | B14: Excluded | C14: Payment processor charges, terminals, SMS credits, lead credits, AI document credits, and third-party app fees are excluded.
A15: Hardware | B15: Excluded | C15: Barcode scanners, receipt printers, cash drawers, tablets, POS terminals, and networking hardware are excluded.
A16: Data migration | B16: Limited active data | C16: Historical transaction migration beyond agreed opening balances and active operational data is excluded.
A17: Payroll | B17: To confirm | C17: US payroll compliance/provider approach must be confirmed before final payroll implementation cost.
A18: Support | B18: 30-day stabilization included | C18: Managed support after stabilization is separate.

Sheet Sources
A1: Sources and Pricing References
A2: Pricing should be validated again with Odoo before contract signature because regional prices and promotions can change.
A4: Source | B4: Reference | C4: Use in Estimate
A5: Meeting notes PDF | B5: Odoo ERP Demo _ Dean Verstegen _ Fox Cities Racquet Club - 2026_07_15 19_59 IST - Notes by Gemini.pdf | C5: Primary source for meeting decisions, next steps, and demo requirements.
A6: Available BRD | B6: Fox Cities Racquet Club - Odoo Business Requirements Document v1 (1).pdf / .txt | C6: Used to validate broader scope and optional full-BRD expansion budget.
A7: Official Odoo pricing | B7: https://www.odoo.com/pricing | C7: Custom plan includes all apps plus Odoo.sh/on-premise option, Studio, multi-company and external API; Odoo.sh hosting is not included in license.
A8: Official Odoo configurator | B8: https://www.odoo.com/pricing-configurator | C8: Used for Custom/Standard annual and monthly planning rates; final quote should be confirmed by billing country.
A9: Official Odoo.sh pricing | B9: https://www.odoo.sh/pricing | C9: Used for Odoo.sh workers, storage, staging environment, and hosting-excludes-license note.
A10: Read-only system check | B10: Configured Odoo database company currency is USD. | C10: Confirmed the configured demo context is USD without creating or modifying records.
